Metadata-Version: 2.1
Name: odoo12-addon-l10n-it-fiscalcode
Version: 12.0.1.1.5
Summary: Italian Localization - Fiscal Code
Home-page: https://github.com/OCA/l10n-italy/tree/12.0/l10n_it_fiscalcode
Author: Link IT s.r.l., Apulia Software, Odoo Italia Network, Odoo Community Association (OCA)
Author-email: support@odoo-community.org
License: AGPL-3
Platform: UNKNOWN
Classifier: Programming Language :: Python
Classifier: Framework :: Odoo
Classifier: Framework :: Odoo :: 12.0
Classifier: License :: OSI Approved :: GNU Affero General Public License v3
Classifier: Development Status :: 5 - Production/Stable
Requires-Python: >=3.5
Requires-Dist: codicefiscale
Requires-Dist: odoo <12.1dev,>=12.0a
